qcloud_setup/__init__.py
qcloud_setup/api-gateway.yaml
qcloud_setup/budget.yaml
qcloud_setup/cognito.yaml
qcloud_setup/iam-policy.yaml
qcloud_setup/qcloud_admin.py
qcloud_setup-1.0.37.data/scripts/qcloud_admin.py
qcloud_setup-1.0.37.dist-info/licenses/LICENSE.txt
qcloud_setup-1.0.37.dist-info/METADATA
qcloud_setup-1.0.37.dist-info/WHEEL
qcloud_setup-1.0.37.dist-info/entry_points.txt
qcloud_setup-1.0.37.dist-info/top_level.txt
qcloud_setup-1.0.37.dist-info/RECORD
