Metadata-Version: 2.4
Name: qcloud_setup
Version: 1.0.37
Summary: Q-Cloud setup utility for cluster administrators
Home-page: https://q-chem.com
Author-email: "Q-Chem Inc." <support@q-chem.com>
Project-URL: Homepage, https://q-chem.com
Keywords: qcloud,qchem,q-cloud,q-chem
Requires-Python: >=3.9
License-File: LICENSE.txt
Requires-Dist: demjson3>=3.0.6
Requires-Dist: paramiko==3.4.0
Requires-Dist: pick>=2.2.0
Requires-Dist: PyYAML==5.3.1
Requires-Dist: pyopenssl>=22.1.0
Requires-Dist: Requests>=2.27.1
Requires-Dist: aws-parallelcluster==3.6.0
Dynamic: home-page
Dynamic: license-file
